randydata/__init__.py
randydata/data_layout.py
randydata/welcome_data.py
randydata-0.3.1.10.dist-info/LICENSE
randydata-0.3.1.10.dist-info/METADATA
randydata-0.3.1.10.dist-info/WHEEL
randydata-0.3.1.10.dist-info/top_level.txt
randydata-0.3.1.10.dist-info/RECORD
