Metadata-Version: 2.1
Name: randydata
Version: 0.3.1.10
Summary: Tools for SQL or Excel of observational data handling.
Home-page: https://github.com/JohannesRanderath/randydata
Author: Johannes Randerath
Author-email: randydata@randerath.eu
License: MIT
Keywords: excel sql data handling
Platform: UNKNOWN
License-File: LICENSE
Requires-Dist: pandas (>=1.4.1)
Requires-Dist: mysql (>=0.0.3)
Requires-Dist: sqlalchemy (>=1.4.32)
Requires-Dist: IPython (>=8.1.1)
Requires-Dist: greenlet (>=1.1.2)
Requires-Dist: numpy (>=1.22.3)
Requires-Dist: python-dateutil (>=2.8.2)
Requires-Dist: pytz (>=2021.3)
Requires-Dist: six (>=1.16.0)
Requires-Dist: appnope (>=0.1.2)
Requires-Dist: backcall (>=0.2.0)
Requires-Dist: decorator (>=5.1.1)
Requires-Dist: jedi (>=0.18.1)
Requires-Dist: parso (>=0.8.3)
Requires-Dist: matplotlib-inline (>=0.1.3)
Requires-Dist: traitlets (>=5.1.1)
Requires-Dist: pexpect (>=4.8.0)
Requires-Dist: ptyprocess (>=0.7.0)
Requires-Dist: pickleshare (>=0.7.5)
Requires-Dist: prompt-toolkit (>=3.0.28)
Requires-Dist: wcwidth (>=0.2.5)
Requires-Dist: pygments (>=2.11.2)
Requires-Dist: setuptools (>=58.1.0)
Requires-Dist: stack-data (>=0.2.0)
Requires-Dist: asttokens (>=2.0.5)
Requires-Dist: executing (>=0.8.3)
Requires-Dist: pure-eval (>=0.2.2)
Requires-Dist: protobuf (>=3.19.4)
Requires-Dist: openpyxl (>=3.0.9)
